llm_fragments_us_legislation.py
llm_fragments_us_legislation-0.1.dist-info/licenses/LICENSE
llm_fragments_us_legislation-0.1.dist-info/METADATA
llm_fragments_us_legislation-0.1.dist-info/WHEEL
llm_fragments_us_legislation-0.1.dist-info/entry_points.txt
llm_fragments_us_legislation-0.1.dist-info/top_level.txt
llm_fragments_us_legislation-0.1.dist-info/RECORD
