Metadata-Version: 2.4
Name: llm-fragments-us-legislation
Version: 0.1
Summary: Load bills from Congress.gov as LLM fragments
Author: Kevin Schaul
License-Expression: Apache-2.0
Project-URL: Homepage, https://github.com/kevinschaul/llm-fragments-us-legislation
Project-URL: Changelog, https://github.com/kevinschaul/llm-fragments-us-legislation/releases
Project-URL: Issues, https://github.com/kevinschaul/llm-fragments-us-legislation/issues
Project-URL: CI, https://github.com/kevinschaul/llm-fragments-us-legislation/actions
Requires-Python: >=3.9
License-File: LICENSE
Requires-Dist: llm
Requires-Dist: httpx
Provides-Extra: test
Requires-Dist: pytest; extra == "test"
Requires-Dist: respx>=0.22.0; extra == "test"
Dynamic: license-file
